odoo/addons/stock_kardex_report/README.rst
odoo/addons/stock_kardex_report/__init__.py
odoo/addons/stock_kardex_report/__manifest__.py
odoo/addons/stock_kardex_report/i18n/stock_kardex_report.pot
odoo/addons/stock_kardex_report/models/__init__.py
odoo/addons/stock_kardex_report/models/stock_kardex_report.py
odoo/addons/stock_kardex_report/readme/CONTRIBUTORS.rst
odoo/addons/stock_kardex_report/readme/DESCRIPTION.rst
odoo/addons/stock_kardex_report/readme/USAGE.rst
odoo/addons/stock_kardex_report/security/ir.model.access.csv
odoo/addons/stock_kardex_report/static/description/icon.png
odoo/addons/stock_kardex_report/static/description/index.html
odoo/addons/stock_kardex_report/views/stock_kardex_report_views.xml
odoo/addons/stock_kardex_report/wizard/__init__.py
odoo/addons/stock_kardex_report/wizard/stock_kardex_report_wizard.py
odoo/addons/stock_kardex_report/wizard/stock_kardex_report_wizard_view.xml
odoo12_addon_stock_kardex_report-12.0.1.0.0.99.dev3.dist-info/METADATA
odoo12_addon_stock_kardex_report-12.0.1.0.0.99.dev3.dist-info/WHEEL
odoo12_addon_stock_kardex_report-12.0.1.0.0.99.dev3.dist-info/top_level.txt
odoo12_addon_stock_kardex_report-12.0.1.0.0.99.dev3.dist-info/RECORD
